nn13framework/__init__.py
nn13framework/data_loader/__init__.py
nn13framework/metrics/__init__.py
nn13framework/neural_networks/__init__.py
nn13framework/neural_networks/activation_functions.py
nn13framework/neural_networks/loss_functions.py
nn13framework/neural_networks/layers/__init__.py
nn13framework/optimizer/__init__.py
nn13framework/utils/__init__.py
nn13framework/visualization/__init__.py
nn13framework-0.0.6.dist-info/METADATA
nn13framework-0.0.6.dist-info/WHEEL
nn13framework-0.0.6.dist-info/top_level.txt
nn13framework-0.0.6.dist-info/RECORD
